json_matcher/__init__.py
json_matcher/exception.py
json_matcher/matcher.py
json_matcher/rule.py
json_matcher/util.py
tests/__init__.py
tests/test_matcher.py
tests/test_rule.py
JsonMatcher-0.0.4.dist-info/LICENSE
JsonMatcher-0.0.4.dist-info/METADATA
JsonMatcher-0.0.4.dist-info/WHEEL
JsonMatcher-0.0.4.dist-info/top_level.txt
JsonMatcher-0.0.4.dist-info/RECORD
