Metadata-Version: 2.1
Name: JsonMatcher
Version: 0.0.4
Summary: A simple json struct matcher
Home-page: https://github.com/Shichao1996
Author: Shichao1996
Author-email: 2483061998@qq.com
License: MIT
Platform: UNKNOWN
Classifier: Programming Language :: Python :: 3
Classifier: License :: OSI Approved :: MIT License
Classifier: Operating System :: OS Independent
